Metadata-Version: 1.1
Name: typec
Version: 0.0.1
Summary: typechecking library
Home-page: https://github.com/tiagocoutinho/typec
Author: Tiago Coutinho
Author-email: coutinhotiago@gmail.com
License: UNKNOWN
Keywords: typing
Platform: UNKNOWN
Classifier: Programming Language :: Python
Classifier: Programming Language :: Python :: 3.5
Classifier: Programming Language :: Python :: 3.6
